OLaunch-0.7.2.data/scripts/run_odoo_code
get_odoo_env/__init__.py
get_odoo_env/get_odoo_env.py
olaunch/__init__.py
olaunch/get_odoo_env.py
OLaunch-0.7.2.dist-info/METADATA
OLaunch-0.7.2.dist-info/WHEEL
OLaunch-0.7.2.dist-info/top_level.txt
OLaunch-0.7.2.dist-info/RECORD
