Metadata-Version: 2.1
Name: OLaunch
Version: 0.7.2
Summary: Odoo tools for Odoo partners
Home-page: https://github.com/olaunchcom/olaunch
Author: OLaunch
Author-email: support@olaunch.com.au
License: UNKNOWN
Platform: UNKNOWN
Classifier: Programming Language :: Python :: 3
Classifier: License :: OSI Approved :: MIT License
Classifier: Operating System :: OS Independent
